rencode/__init__.py
rencode/_rencode.cpython-313-x86_64-linux-gnu.so
rencode/_rencode.pyx
rencode/rencode_orig.py
rencode-1.0.8.dist-info/COPYING
rencode-1.0.8.dist-info/METADATA
rencode-1.0.8.dist-info/WHEEL
rencode-1.0.8.dist-info/RECORD
