Metadata-Version: 2.3
Name: rencode
Version: 1.0.8
Summary: rencode is an object serialization library similar to bencode from the Bittorrent project.
License: GPLv3
Author: Andrew Resch
Author-email: andrewresch@gmail.com
Requires-Python: >=3.9,<4.0
Classifier: License :: Other/Proprietary License
Classifier: Programming Language :: Python :: 3
Classifier: Programming Language :: Python :: 3.9
Classifier: Programming Language :: Python :: 3.10
Classifier: Programming Language :: Python :: 3.11
Classifier: Programming Language :: Python :: 3.12
Classifier: Programming Language :: Python :: 3.13
